LICENSE
MANIFEST.in
README.md
requirements.txt
setup.cfg
setup.py
seanalgorithms/__init__.py
seanalgorithms2.egg-info/PKG-INFO
seanalgorithms2.egg-info/SOURCES.txt
seanalgorithms2.egg-info/dependency_links.txt
seanalgorithms2.egg-info/not-zip-safe
seanalgorithms2.egg-info/requires.txt
seanalgorithms2.egg-info/top_level.txt
seanalgorithms/algorithms_practice/__init__.py
seanalgorithms/algorithms_practice/arithmetic_analysis/__init__.py
seanalgorithms/algorithms_practice/arithmetic_analysis/bisection.py
seanalgorithms/algorithms_practice/arithmetic_analysis/gaussian_elimination.py
seanalgorithms/algorithms_practice/arithmetic_analysis/in_static_equilibrium.py
seanalgorithms/algorithms_practice/arithmetic_analysis/intersection.py
seanalgorithms/algorithms_practice/arithmetic_analysis/lu_decomposition.py
seanalgorithms/algorithms_practice/arithmetic_analysis/newton_forward_interpolation.py
seanalgorithms/algorithms_practice/arithmetic_analysis/newton_method.py
seanalgorithms/algorithms_practice/arithmetic_analysis/newton_raphson.py
seanalgorithms/algorithms_practice/arithmetic_analysis/secant_method.py
seanalgorithms/algorithms_practice/arithmetic_analysis/image_data/__init__.py
seanalgorithms/algorithms_practice/backtracking/__init__.py
seanalgorithms/algorithms_practice/backtracking/all_combinations.py
seanalgorithms/algorithms_practice/backtracking/all_permutations.py
seanalgorithms/algorithms_practice/backtracking/all_subsequences.py
seanalgorithms/algorithms_practice/backtracking/coloring.py
seanalgorithms/algorithms_practice/backtracking/hamiltonian_cycle.py
seanalgorithms/algorithms_practice/backtracking/knight_tour.py
seanalgorithms/algorithms_practice/backtracking/minimax.py
seanalgorithms/algorithms_practice/backtracking/n_queens.py
seanalgorithms/algorithms_practice/backtracking/n_queens_math.py
seanalgorithms/algorithms_practice/backtracking/rat_in_maze.py
seanalgorithms/algorithms_practice/backtracking/sudoku.py
seanalgorithms/algorithms_practice/backtracking/sum_of_subsets.py
seanalgorithms/algorithms_practice/bit_manipulation/__init__.py
seanalgorithms/algorithms_practice/bit_manipulation/binary_and_operator.py
