Metadata-Version: 2.1
Name: seanalgorithms2
Version: 0.1
Summary: Python algorithms
Home-page: https://github.com/seanlab3/algorithms2
Author: seanlab
Author-email: seanlabcoding33@gmail.com
License: UNKNOWN
Platform: UNKNOWN
Classifier: License :: OSI Approved :: MIT License
License-File: LICENSE
